{
  "entityType" : "DEVICE",
  "entity" : {
    "additionalInfo" : {
      "description" : "Demo device that is used in Raspberry Pi GPIO control sample application"
    },
    "customerId" : {
      "entityType" : "CUSTOMER",
      "id" : "13814000-1dd2-11b2-8080-808080808080"
    },
    "deviceData" : {
      "configuration" : {
        "type" : "DEFAULT"
      },
      "transportConfiguration" : {
        "type" : "DEFAULT"
      }
    },
    "deviceProfileId" : {
      "entityType" : "DEVICE_PROFILE",
      "id" : "39dd09f0-7c96-11ee-b7c2-9fd88b340a2e"
    },
    "externalId" : null,
    "firmwareId" : null,
    "id" : {
      "entityType" : "DEVICE",
      "id" : "3b391780-7c96-11ee-b7c2-9fd88b340a2e"
    },
    "label" : null,
    "name" : "Raspberry Pi Demo Device",
    "ownerId" : null,
    "softwareId" : null,
    "type" : "default"
  },
  "credentials" : {
    "credentialsId" : "RASPBERRY_PI_DEMO_TOKEN",
    "credentialsType" : "ACCESS_TOKEN",
    "credentialsValue" : null
  },
  "relations" : [ ],
  "attributes" : {
    "SERVER_SCOPE" : [ {
      "booleanValue" : false,
      "doubleValue" : null,
      "jsonValue" : null,
      "key" : "active",
      "lastUpdateTs" : 1699270157662,
      "longValue" : null,
      "strValue" : null
    }, {
      "booleanValue" : null,
      "doubleValue" : null,
      "jsonValue" : null,
      "key" : "inactivityAlarmTime",
      "lastUpdateTs" : 1699270157674,
      "longValue" : 1699270157112,
      "strValue" : null
    } ],
    "SHARED_SCOPE" : [ ]
  }
}